{"mean":{"confidence_interval":{"confidence_level":0.95,"lower_bound":36959370.85648148,"upper_bound":37242138.11148148},"point_estimate":37075893.72564815,"standard_error":75123.07968931264},"median":{"confidence_interval":{"confidence_level":0.95,"lower_bound":36952121.52083333,"upper_bound":37104396.71666667},"point_estimate":36995876.3,"standard_error":44470.06833783677},"median_abs_dev":{"confidence_interval":{"confidence_level":0.95,"lower_bound":9409.705110724983,"upper_bound":235750.6433945887},"point_estimate":71370.72569542001,"standard_error":60271.23531397552},"slope":{"confidence_interval":{"confidence_level":0.95,"lower_bound":36951132.35149864,"upper_bound":37061349.04549214},"point_estimate":37006328.34718615,"standard_error":29745.192301080195},"std_dev":{"confidence_interval":{"confidence_level":0.95,"lower_bound":55984.36353547007,"upper_bound":375879.3097078032},"point_estimate":251711.44634623558,"standard_error":99156.92964946109}}