{"mean":{"confidence_interval":{"confidence_level":0.95,"lower_bound":21344503.366,"upper_bound":24534696.30042857},"point_estimate":23102583.99426984,"standard_error":822204.4994696432},"median":{"confidence_interval":{"confidence_level":0.95,"lower_bound":21887999.72,"upper_bound":25258522.457142856},"point_estimate":23624451.75777778,"standard_error":855903.7603836261},"median_abs_dev":{"confidence_interval":{"confidence_level":0.95,"lower_bound":532686.8731309187,"upper_bound":3853846.7475262093},"point_estimate":2498568.460685543,"standard_error":878684.8989829354},"slope":{"confidence_interval":{"confidence_level":0.95,"lower_bound":22661470.432698425,"upper_bound":24916213.682932604},"point_estimate":23948345.396363635,"standard_error":569356.3715005819},"std_dev":{"confidence_interval":{"confidence_level":0.95,"lower_bound":1106611.4084630862,"upper_bound":3803329.278171189},"point_estimate":2746215.328498602,"standard_error":772015.8655940578}}